diff_risk_dashboard/__init__.py
diff_risk_dashboard/__main__.py
diff_risk_dashboard/cli.py
diff_risk_dashboard/core.py
diff_risk_dashboard/report.py
diff_risk_dashboard-0.4.37.dist-info/METADATA
diff_risk_dashboard-0.4.37.dist-info/WHEEL
diff_risk_dashboard-0.4.37.dist-info/entry_points.txt
diff_risk_dashboard-0.4.37.dist-info/licenses/LICENSE
diff_risk_dashboard-0.4.37.dist-info/licenses/NOTICE
diff_risk_dashboard-0.4.37.dist-info/RECORD
