Metadata-Version: 2.4
Name: diff-risk-dashboard
Version: 0.4.37
Summary: Visual risk exposure of PRs powered by ai-patch-verifier outputs.
License: MIT
License-File: LICENSE
License-File: NOTICE
Author: CoderDeltaLAN
Author-email: coderdeltalan.cargo784@8alias.com
Requires-Python: >=3.11,<3.13
Classifier: License :: OSI Approved :: MIT License
Classifier: Programming Language :: Python :: 3
Classifier: Programming Language :: Python :: 3.11
Classifier: Programming Language :: Python :: 3.12
Requires-Dist: pydantic (>=2,<3)
Requires-Dist: rich (>=13,<15)
